pyonce.py
pyonce-1.0.0.dist-info/LICENSE
pyonce-1.0.0.dist-info/METADATA
pyonce-1.0.0.dist-info/WHEEL
pyonce-1.0.0.dist-info/top_level.txt
pyonce-1.0.0.dist-info/RECORD
