Metadata-Version: 2.1
Name: pyonce
Version: 1.0.0
Summary: Run code once!
Home-page: https://github.com/szabolcsdombi/pyonce/
Author: Szabolcs Dombi
Author-email: cprogrammer1994@gmail.com
License: MIT
Project-URL: Documentation, https://github.com/szabolcsdombi/pyonce/#readme
Project-URL: Source, https://github.com/szabolcsdombi/pyonce/blob/main/pyonce.py
Project-URL: Bug Tracker, https://github.com/szabolcsdombi/pyonce/issues/
Keywords: once
Platform: any
Classifier: Programming Language :: Python :: 3
Classifier: License :: OSI Approved :: MIT License
Classifier: Operating System :: OS Independent
License-File: LICENSE
